sentience/__init__.py
sentience/actions.py
sentience/browser.py
sentience/cli.py
sentience/expect.py
sentience/generator.py
sentience/inspector.py
sentience/models.py
sentience/query.py
sentience/read.py
sentience/recorder.py
sentience/screenshot.py
sentience/snapshot.py
sentience/wait.py
sentience_python-0.10.6.dist-info/METADATA
sentience_python-0.10.6.dist-info/WHEEL
sentience_python-0.10.6.dist-info/entry_points.txt
sentience_python-0.10.6.dist-info/top_level.txt
sentience_python-0.10.6.dist-info/RECORD
