Metadata-Version: 2.4
Name: sentience-python
Version: 0.10.6
Summary: Python SDK for Sentience AI Agent Browser Automation
Author: Sentience Team
License: MIT
Project-URL: Homepage, https://github.com/SentienceAPI/sentience-python
Project-URL: Repository, https://github.com/SentienceAPI/sentience-python
Project-URL: Issues, https://github.com/SentienceAPI/sentience-python/issues
Keywords: browser-automation,playwright,ai-agent,web-automation,sentience
Classifier: Development Status :: 4 - Beta
Classifier: Intended Audience :: Developers
Classifier: License :: OSI Approved :: MIT License
Classifier: Programming Language :: Python :: 3
Classifier: Programming Language :: Python :: 3.11
Requires-Python: >=3.11
Requires-Dist: playwright>=1.40.0
Requires-Dist: pydantic>=2.0.0
Requires-Dist: jsonschema>=4.0.0
Requires-Dist: requests>=2.31.0
Requires-Dist: playwright-stealth>=1.0.6
Requires-Dist: markdownify>=0.11.6
Provides-Extra: dev
Requires-Dist: pytest>=7.0.0; extra == "dev"
Requires-Dist: pytest-asyncio>=0.21.0; extra == "dev"
